mcda/__init__.py
mcda/core/__init__.py
mcda/core/aliases.py
mcda/core/functions.py
mcda/core/performance_table.py
mcda/core/scales.py
mcda/core/set_functions.py
mcda/core/sets.py
mcda/core/sorting.py
mcda/electre/__init__.py
mcda/electre/_validation.py
mcda/electre/concordance.py
mcda/electre/credibility.py
mcda/electre/discordance.py
mcda/electre/exceptions.py
mcda/electre/plot.py
mcda/electre/utils.py
mcda/electre/outranking/__init__.py
mcda/electre/outranking/choice.py
mcda/electre/outranking/crisp_outranking.py
mcda/electre/outranking/ranking.py
mcda/electre/outranking/sorting.py
electre_methods-0.1.0.dist-info/LICENCE
electre_methods-0.1.0.dist-info/METADATA
electre_methods-0.1.0.dist-info/WHEEL
electre_methods-0.1.0.dist-info/top_level.txt
electre_methods-0.1.0.dist-info/RECORD
