Metadata-Version: 2.1
Name: electre-methods
Version: 0.1.0
Summary: Package with broad spectrum of elementary ELECTRE-based modules that can be joined together in many different combinations and used via a user-friendly Python library
Author-email: Agnieszka Klimek <aga.klimek.klimek@gmail.com>, Anna Prałat <anna@pralat.pl>, Patryk Hubicki <zie.patryk@gmail.com>, Tomasz Budner <tomasz.budner.ad@gmail.com>
Project-URL: Homepage, https://github.com/PatrykHub/ELECTRE-Methods
Project-URL: Bug Tracker, https://github.com/PatrykHub/ELECTRE-Methods/issues
Classifier: Programming Language :: Python :: 3
Classifier: License :: OSI Approved :: MIT License
Classifier: Operating System :: OS Independent
Requires-Python: >=3.8
License-File: LICENCE
Requires-Dist: graphviz >=0.20.1
Requires-Dist: networkx >=3.1
Requires-Dist: numpy >=1.19.5 ; python_version <= "3.9"
Requires-Dist: pandas >=1.1.5 ; python_version <= "3.9"
Requires-Dist: numpy >=1.21.3 ; python_version == "3.10"
Requires-Dist: pandas >=1.4 ; python_version == "3.10"
Requires-Dist: numpy >=1.23.2 ; python_version >= "3.11"
Requires-Dist: pandas >=1.5 ; python_version >= "3.11"
